gradle.properties
hexdoc_hextrace/__gradle_version__.py
hexdoc_hextrace/__init__.py
hexdoc_hextrace/__version__.py
hexdoc_hextrace/_hooks.py
hexdoc_hextrace/py.typed
hexdoc_hextrace/_export/.gitignore
hexdoc_hextrace/_export/__init__.py
hexdoc_hextrace/_export/generated/__init__.py
hexdoc_hextrace/_export/generated/hextrace.hexdoc.json
hexdoc_hextrace/_export/generated/hextrace.patterns.hexdoc.json
hexdoc_hextrace/_export/generated/assets/hexcasting/patchouli_books/thehexbook/en_us/entries/patterns/traces.json
hexdoc_hextrace/_export/generated/assets/hextrace/lang/en_us.flatten.json5
hexdoc_hextrace/_templates/__init__.py
hexdoc_hextrace-0.1.0.1.20.1.1.0.dist-info/METADATA
hexdoc_hextrace-0.1.0.1.20.1.1.0.dist-info/WHEEL
hexdoc_hextrace-0.1.0.1.20.1.1.0.dist-info/entry_points.txt
hexdoc_hextrace-0.1.0.1.20.1.1.0.dist-info/licenses/LICENSE
hexdoc_hextrace-0.1.0.1.20.1.1.0.dist-info/RECORD
