Metadata-Version: 2.4
Name: hexdoc-hextrace
Version: 0.1.0.1.20.1.1.0
Summary: Hex Trace addon for Hex Casting
Project-URL: Homepage, https://ducklingvivi.github.io/HexTrace
Project-URL: Source, https://github.com/DucklingVivi/HexTrace
Author: DucklingVivi
License-File: LICENSE
Keywords: hexdoc
Requires-Python: >=3.12
Requires-Dist: hexdoc-hexcasting~=0.11.2.1.0
